keyphrase_vectorizers/__init__.py
keyphrase_vectorizers/_version.py
keyphrase_vectorizers/keyphrase_count_vectorizer.py
keyphrase_vectorizers/keyphrase_tfidf_vectorizer.py
keyphrase_vectorizers/keyphrase_vectorizer_mixin.py
keyphrase_vectorizers-0.0.13.data/data/requirements/requirements.txt
tests/__init__.py
tests/test_vectorizers.py
tests/utils.py
keyphrase_vectorizers-0.0.13.dist-info/LICENSE
keyphrase_vectorizers-0.0.13.dist-info/METADATA
keyphrase_vectorizers-0.0.13.dist-info/WHEEL
keyphrase_vectorizers-0.0.13.dist-info/top_level.txt
keyphrase_vectorizers-0.0.13.dist-info/RECORD
